sim_bug_tools/__init__.py
sim_bug_tools/constants.py
sim_bug_tools/decorators.py
sim_bug_tools/graphics.py
sim_bug_tools/lshash.py
sim_bug_tools/structs.py
sim_bug_tools/utils.py
sim_bug_tools/experiment/__init__.py
sim_bug_tools/experiment/experiment.py
sim_bug_tools/exploration/__init__.py
sim_bug_tools/exploration/brute_force.py
sim_bug_tools/exploration/boundary_core/__init__.py
sim_bug_tools/exploration/boundary_core/adherer.py
sim_bug_tools/exploration/boundary_core/explorer.py
sim_bug_tools/exploration/boundary_core/surfacer.py
sim_bug_tools/exploration/brrt_std/__init__.py
sim_bug_tools/exploration/brrt_std/adherer.py
sim_bug_tools/exploration/brrt_std/brrt.py
sim_bug_tools/exploration/brrt_v2/__init__.py
sim_bug_tools/exploration/brrt_v2/adherer.py
sim_bug_tools/rng/__init__.py
sim_bug_tools/rng/bugger.py
sim_bug_tools/rng/rrt.py
sim_bug_tools/rng/lds/__init__.py
sim_bug_tools/rng/lds/coverage.py
sim_bug_tools/rng/lds/sequences.py
sim_bug_tools-1.0.1.dist-info/LICENSE
sim_bug_tools-1.0.1.dist-info/METADATA
sim_bug_tools-1.0.1.dist-info/WHEEL
sim_bug_tools-1.0.1.dist-info/top_level.txt
sim_bug_tools-1.0.1.dist-info/RECORD
