Metadata-Version: 2.1
Name: sim-bug-tools
Version: 1.0.1
Summary: A toolkit for exploring bugs in software simulations.
Home-page: https://github.com/AkbasLab/sim-bug-tools
Author: Quentin Goss, John Thompson, Dr. Mustafa Ilhan Akbas
Author-email: gossq@my.erau.edu, thomj130@my.erau.edu, akbasm@erau.edu
Project-URL: Bug Tracker, https://github.com/AkbasLab/sim-bug-tools/issues
Classifier: Programming Language :: Python :: 3
Classifier: License :: OSI Approved :: MIT License
Classifier: Operating System :: OS Independent
Requires-Python: >= 3.9
License-File: LICENSE
Requires-Dist: numpy >=1.21.1
Requires-Dist: matplotlib >=3.4.2
Requires-Dist: scipy >=1.7.1
Requires-Dist: scikit-learn >=0.24.2
Requires-Dist: networkx >=2.6.2
Requires-Dist: pandas >=1.3.2
Requires-Dist: openturns >=1.17
Requires-Dist: treelib >=1.6.1
Requires-Dist: Rtree >=1.0.0
